[
  {
    "full_name": "ngrx/platform",
    "stargazers_count": 8307,
    "open_issues_count": 69,
    "forks_count": 2049
  },
  {
    "full_name": "wangel13/taras.one",
    "stargazers_count": 2,
    "open_issues_count": 0,
    "forks_count": 0
  },
  {
    "full_name": "EddieHubCommunity/BioDrop",
    "stargazers_count": 5724,
    "open_issues_count": 72,
    "forks_count": 4050
  },
  {
    "full_name": "collabnix/kubelabs",
    "stargazers_count": 3076,
    "open_issues_count": 9,
    "forks_count": 1122
  },
  {
    "full_name": "sudheerj/reactjs-interview-questions",
    "stargazers_count": 44392,
    "open_issues_count": 10,
    "forks_count": 10304
  },
  {
    "full_name": "responsively-org/responsively-app",
    "stargazers_count": 24812,
    "open_issues_count": 292,
    "forks_count": 1339
  },
  {
    "full_name": "danthareja/contribute-to-open-source",
    "stargazers_count": 1478,
    "open_issues_count": 202,
    "forks_count": 1785
  },
  {
    "full_name": "freeCodeCamp/how-to-contribute-to-open-source",
    "stargazers_count": 9314,
    "open_issues_count": 90,
    "forks_count": 1869
  },
  {
    "full_name": "Ovi/DummyJSON",
    "stargazers_count": 2719,
    "open_issues_count": 10,
    "forks_count": 284
  },
  {
    "full_name": "mann-codes2014/social-media-dashboard",
    "stargazers_count": 1,
    "open_issues_count": 0,
    "forks_count": 0
  },
  {
    "full_name": "mann-codes2014/blogr-landing-page-main",
    "stargazers_count": 1,
    "open_issues_count": 0,
    "forks_count": 0
  },
  {
    "full_name": "storybookjs/storybook",
    "stargazers_count": 89503,
    "open_issues_count": 2217,
    "forks_count": 9935
  },
  {
    "full_name": "mann-codes2014/first-contributions",
    "stargazers_count": 2,
    "open_issues_count": 1,
    "forks_count": 1
  },
  {
    "full_name": "firstcontributions/first-contributions",
    "stargazers_count": 53134,
    "open_issues_count": 134,
    "forks_count": 100054
  }
]