[
  {
    "full_name": "ngrx/platform",
    "stargazers_count": 8258,
    "open_issues_count": 71,
    "forks_count": 2042
  },
  {
    "full_name": "wangel13/taras.one",
    "stargazers_count": 2,
    "open_issues_count": 0,
    "forks_count": 0
  },
  {
    "full_name": "EddieHubCommunity/BioDrop",
    "stargazers_count": 5734,
    "open_issues_count": 72,
    "forks_count": 4024
  },
  {
    "full_name": "collabnix/kubelabs",
    "stargazers_count": 3036,
    "open_issues_count": 9,
    "forks_count": 1102
  },
  {
    "full_name": "sudheerj/reactjs-interview-questions",
    "stargazers_count": 43219,
    "open_issues_count": 6,
    "forks_count": 10106
  },
  {
    "full_name": "responsively-org/responsively-app",
    "stargazers_count": 24355,
    "open_issues_count": 283,
    "forks_count": 1306
  },
  {
    "full_name": "danthareja/contribute-to-open-source",
    "stargazers_count": 1460,
    "open_issues_count": 198,
    "forks_count": 1776
  },
  {
    "full_name": "freeCodeCamp/how-to-contribute-to-open-source",
    "stargazers_count": 9070,
    "open_issues_count": 83,
    "forks_count": 1862
  },
  {
    "full_name": "Ovi/DummyJSON",
    "stargazers_count": 2512,
    "open_issues_count": 11,
    "forks_count": 268
  },
  {
    "full_name": "mann-codes2014/social-media-dashboard",
    "stargazers_count": 1,
    "open_issues_count": 0,
    "forks_count": 0
  },
  {
    "full_name": "mann-codes2014/blogr-landing-page-main",
    "stargazers_count": 1,
    "open_issues_count": 0,
    "forks_count": 0
  },
  {
    "full_name": "storybookjs/storybook",
    "stargazers_count": 88199,
    "open_issues_count": 2228,
    "forks_count": 9733
  },
  {
    "full_name": "mann-codes2014/first-contributions",
    "stargazers_count": 2,
    "open_issues_count": 1,
    "forks_count": 1
  },
  {
    "full_name": "firstcontributions/first-contributions",
    "stargazers_count": 50923,
    "open_issues_count": 142,
    "forks_count": 92918
  }
]