[
  {
    "full_name": "collabnix/kubelabs",
    "stargazers_count": 1874,
    "open_issues_count": 5,
    "forks_count": 696
  },
  {
    "full_name": "sudheerj/reactjs-interview-questions",
    "stargazers_count": 28240,
    "open_issues_count": 7,
    "forks_count": 6981
  },
  {
    "full_name": "responsively-org/responsively-app",
    "stargazers_count": 19420,
    "open_issues_count": 141,
    "forks_count": 851
  },
  {
    "full_name": "danthareja/contribute-to-open-source",
    "stargazers_count": 1084,
    "open_issues_count": 154,
    "forks_count": 1342
  },
  {
    "full_name": "freeCodeCamp/how-to-contribute-to-open-source",
    "stargazers_count": 7476,
    "open_issues_count": 47,
    "forks_count": 1611
  },
  {
    "full_name": "Ovi/DummyJSON",
    "stargazers_count": 511,
    "open_issues_count": 3,
    "forks_count": 81
  },
  {
    "full_name": "mann-codes2014/social-media-dashboard",
    "stargazers_count": 1,
    "open_issues_count": 0,
    "forks_count": 0
  },
  {
    "full_name": "mann-codes2014/blogr-landing-page-main",
    "stargazers_count": 1,
    "open_issues_count": 0,
    "forks_count": 0
  },
  {
    "full_name": "storybookjs/storybook",
    "stargazers_count": 77639,
    "open_issues_count": 2055,
    "forks_count": 8254
  },
  {
    "full_name": "mann-codes2014/first-contributions",
    "stargazers_count": 2,
    "open_issues_count": 1,
    "forks_count": 1
  },
  {
    "full_name": "firstcontributions/first-contributions",
    "stargazers_count": 32517,
    "open_issues_count": 361,
    "forks_count": 57968
  }
]